arctic_charr_matcher/DBUtil.py
arctic_charr_matcher/LengthMatcher.py
arctic_charr_matcher/Matcher.py
arctic_charr_matcher/Patch.py
arctic_charr_matcher/UnetExtractor.py
arctic_charr_matcher/__init__.py
arctic_charr_matcher/algorithms.py
arctic_charr_matcher/astroalign.py
arctic_charr_matcher/astroalignMatch.py
arctic_charr_matcher/fish.py
arctic_charr_matcher/grothMatcherCustom.py
arctic_charr_matcher/tester.py
arctic_charr_matcher/util.py
arctic_charr_matcher-0.1.4.dist-info/LICENSE
arctic_charr_matcher-0.1.4.dist-info/METADATA
arctic_charr_matcher-0.1.4.dist-info/WHEEL
arctic_charr_matcher-0.1.4.dist-info/top_level.txt
arctic_charr_matcher-0.1.4.dist-info/RECORD
