Metadata-Version: 2.1
Name: arctic_charr_matcher
Version: 0.1.4
Summary: Arctic Charr matching library
Home-page: https://github.com/walker-herndon/Arctic_charr_packaged
Author: Walker Herndon
Author-email: Walker Herndon <walker.herndon01@gmail.com>
Project-URL: Homepage, https://github.com/walker-herndon/arctic-charr-packaged
Project-URL: Issues, https://github.com/walker-herndon/arctic-charr-packaged/issues
Classifier: Programming Language :: Python :: 3
Classifier: License :: OSI Approved :: MIT License
Classifier: Operating System :: OS Independent
Requires-Python: >=3.8
License-File: LICENSE
Requires-Dist: notebook >=7.0.0
Requires-Dist: numpy <2.0.0,>=1.26.0
Requires-Dist: matplotlib <4.0.0,>=3.8.0
Requires-Dist: opencv-python-headless <5.0.0,>=4.8.1.78
Requires-Dist: tensorflow <3.0.0,>=2.10.0
Requires-Dist: keras <3.0.0,>=2.10.0
Requires-Dist: keras-unet <0.2.0,>=0.1.2
Requires-Dist: scikit-image <0.23.0,>=0.22.0
Requires-Dist: scikit-learn <2.0.0,>=1.3.2
Requires-Dist: scipy <2.0.0,>=1.11.0
Requires-Dist: pandas <3.0.0,>=2.1.3
Requires-Dist: xlrd <3.0.0,>=2.0.1
Requires-Dist: sep <2.0.0,>=1.2.1
